retropass/__init__.py
retropass/__main__.py
retropass/cli.py
retropass/password.py
retropass/text.py
retropass/util.py
retropass/version.py
retropass/game/bo.tbl
retropass/game/bo.tsv
retropass/game/ki.tbl
retropass/game/ki.tsv
retropass/game/metroid.tbl
retropass/game/metroid.tsv
retropass/game/mm2.tsv
retropass/game/mm3.tsv
retropass/game/sj.tsv
retropass-0.6.1.dist-info/METADATA
retropass-0.6.1.dist-info/WHEEL
retropass-0.6.1.dist-info/entry_points.txt
retropass-0.6.1.dist-info/top_level.txt
retropass-0.6.1.dist-info/RECORD
