Metadata-Version: 2.1
Name: retropass
Version: 0.6.1
Summary: Library and tool for generating progress passwords for old games
Home-page: https://pypi.org/project/retropass/
Author: Andrew Vant
Author-email: ajvant@gmail.com
License: UNKNOWN
Keywords: rom roms nes
Platform: UNKNOWN
Classifier: Development Status :: 4 - Beta
Classifier: Intended Audience :: Developers
Classifier: Natural Language :: English
Classifier: Operating System :: OS Independent
Classifier: Programming Language :: Python :: 3
Classifier: Topic :: Software Development :: Libraries :: Python Modules
Requires-Dist: bitarray-hardbyte (>=1.5.0)
Requires-Dist: pyyaml (>=3.10)
